yggflix/__init__.py
yggflix/settings.py
yggflix/yggflix.py
yggflix/yggflix_api.py
yggflix/yggflix_result.py
yggflix/yggflix_service.py
yggflix/utils/detection.py
yggflix/utils/torrent_item.py
yggflix/utils/models/media.py
yggflix/utils/models/movie.py
yggflix/utils/models/series.py
yggflix-0.1.2.dist-info/METADATA
yggflix-0.1.2.dist-info/WHEEL
yggflix-0.1.2.dist-info/top_level.txt
yggflix-0.1.2.dist-info/RECORD
