Metadata-Version: 2.4
Name: yggflix
Version: 0.1.2
Summary: API client for YggTorrent with smart torrent selection
Author-email: jletallec <jletallec@icloud.com>
License: MIT
Project-URL: Homepage, https://github.com/jletallec/yggflix
Project-URL: Repository, https://github.com/jletallec/yggflix
Project-URL: Issues, https://github.com/jletallec/yggflix/issues
Keywords: yggtorrent,yggflix
Classifier: Development Status :: 4 - Beta
Classifier: Intended Audience :: Developers
Classifier: License :: OSI Approved :: MIT License
Classifier: Programming Language :: Python :: 3
Classifier: Programming Language :: Python :: 3.8
Classifier: Programming Language :: Python :: 3.9
Classifier: Programming Language :: Python :: 3.10
Classifier: Programming Language :: Python :: 3.11
Classifier: Programming Language :: Python :: 3.12
Requires-Python: >=3.8
Requires-Dist: requests>=2.32.0
Requires-Dist: pydantic>=2.11.0
Requires-Dist: arrow>=1.3.0
Requires-Dist: orjson>=3.11.0
Requires-Dist: parsett>=1.6.15
Requires-Dist: pymediainfo>=7.0.1
Requires-Dist: python-dateutil>=2.9.0
Requires-Dist: rank-torrent-name>=1.9.0
Requires-Dist: rapidfuzz>=3.13.0
Requires-Dist: regex>=2023.12.25
Requires-Dist: levenshtein>=0.27.1
Provides-Extra: dev
Requires-Dist: pytest>=7.0; extra == "dev"
Requires-Dist: pytest-cov; extra == "dev"
Requires-Dist: black; extra == "dev"
Requires-Dist: isort; extra == "dev"
Requires-Dist: flake8; extra == "dev"
